crashs/__init__.py
crashs/__main__.py
crashs/build_template.py
crashs/crashs.py
crashs/derive_template.py
crashs/df.py
crashs/lddmm.py
crashs/omt.py
crashs/preprocess_t2.py
crashs/profile_sampling.py
crashs/roi_integrate.py
crashs/util.py
crashs/vtkutil.py
crashs/param/template_defaults.json
crashs/upsample/upsample_net.py
crashs-0.2.17.dist-info/METADATA
crashs-0.2.17.dist-info/WHEEL
crashs-0.2.17.dist-info/licenses/LICENSE
crashs-0.2.17.dist-info/RECORD
