Metadata-Version: 2.4
Name: crashs
Version: 0.2.17
Summary: CRASHS: Cortical Reconstruction for Automated Segmentation of Hippocampal Subfields (ASHS)
Project-URL: Homepage, https://github.com/pyushkevich/crashs
Author-email: Paul Yushkevich <pyushkevich@gmail.com>
License-File: LICENSE
Classifier: Development Status :: 4 - Beta
Classifier: Intended Audience :: Science/Research
Classifier: License :: OSI Approved :: MIT License
Classifier: Operating System :: OS Independent
Classifier: Programming Language :: Python :: 3
Classifier: Topic :: Scientific/Engineering :: Medical Science Apps.
Requires-Python: >=3.8
Requires-Dist: acvl-utils==0.2
Requires-Dist: blosc2
Requires-Dist: geomloss
Requires-Dist: huggingface-hub==0.36.0
Requires-Dist: monai
Requires-Dist: nnunetv2>=2.3.1
Requires-Dist: numpy
Requires-Dist: picsl-c3d>=1.4.2.1
Requires-Dist: picsl-cmrep>=1.0.4.0
Requires-Dist: picsl-greedy>=0.0.5
Requires-Dist: pykeops
Requires-Dist: pymeshlab
Requires-Dist: python-gdcm==3.0.23.1
Requires-Dist: simpleitk
Requires-Dist: statsmodels
Requires-Dist: torch>=2.0
Requires-Dist: vtk
